eval_rag/__init__.py
eval_rag/eval_rag.py
eval_rag/test_eval_rag.py
eval_rag-0.0.2.dist-info/METADATA
eval_rag-0.0.2.dist-info/WHEEL
eval_rag-0.0.2.dist-info/top_level.txt
eval_rag-0.0.2.dist-info/RECORD
