Metadata-Version: 2.4
Name: eval-rag
Version: 0.0.2
Summary: A comprehensive evaluation toolkit for assessing Retrieval-Augmented Generation (RAG) outputs using linguistic, semantic, and fairness metrics
Home-page: https://github.com/shaadclt/EvalRAG
Author: Mohamed Shaad
Author-email: shaadclt@gmail.com
License: MIT
Classifier: Programming Language :: Python :: 3
Classifier: License :: OSI Approved :: MIT License
Classifier: Operating System :: OS Independent
Requires-Python: >=3.10
Requires-Dist: torch
Requires-Dist: sacrebleu
Requires-Dist: rouge-score
Requires-Dist: bert-score
Requires-Dist: transformers
Requires-Dist: nltk
Requires-Dist: textblob
Requires-Dist: textstat
Dynamic: author
Dynamic: author-email
Dynamic: classifier
Dynamic: description
Dynamic: description-content-type
Dynamic: home-page
Dynamic: license
Dynamic: requires-dist
Dynamic: requires-python
Dynamic: summary
